{"evidence_sha256":"e7e76d9a846efd7eeaae2b06641e170c15878f7cbf1ff98a79a733b1aa451142","participant_id":"participant-04","protocol_sha256":"40afa46f4be87f2573148ce3ff12254e3761e51cf8f849fbeb59c2e585ff6cee","schema_version":"qa-evidence@2","score":{"assisted_success":{"ci_high":"f:0.9544139373553638","ci_low":"f:0.30063605244263664","ci_method":"wilson95","k":3,"n":4,"rate":"f:0.75"},"ci_method":"percentile-bootstrap95","conclusion":"savings","evaluated_pairs":4,"manual_success":{"ci_high":"f:0.48990002040399916","ci_low":"f:0","ci_method":"wilson95","k":0,"n":4,"rate":"f:0"},"mean_saved_fraction":"f:0.42594994681041665","mean_saved_minutes":"f:3.407599574483333","median_saved_fraction":"f:0.5254891183604167","median_saved_minutes":"f:4.203912946883333","pairs":[{"assisted_active_minutes":"f:4.44415662985","assisted_correct":true,"assisted_scored_minutes":"f:4.44415662985","assisted_session_id":"qa-retest-04-session-02","defect_class":"cyclic_dependency","manual_active_minutes":"f:7.370633125","manual_correct":false,"manual_scored_minutes":"f:8","manual_session_id":"qa-retest-04-session-01","pair_id":"qa-retest-04-pair-01","pair_sha256":"7c91eabde8c7e6e64a969772a354bb7e4d84b8720e46f1def21cf8ffdf42970e","saved_fraction":"f:0.44448042126875","saved_minutes":"f:3.55584337015"},{"assisted_active_minutes":"f:2.777427595833333","assisted_correct":true,"assisted_scored_minutes":"f:2.777427595833333","assisted_session_id":"qa-retest-04-session-03","defect_class":"dangling_reference","manual_active_minutes":"f:5.440701004866667","manual_correct":false,"manual_scored_minutes":"f:8","manual_session_id":"qa-retest-04-session-04","pair_id":"qa-retest-04-pair-02","pair_sha256":"8649c755f3345e6cd06f138c04233344c84ca67c452addeefe3eeffb327da85c","saved_fraction":"f:0.6528215505208333","saved_minutes":"f:5.222572404166667"},{"assisted_active_minutes":"f:3.1480174763833335","assisted_correct":true,"assisted_scored_minutes":"f:3.1480174763833335","assisted_session_id":"qa-retest-04-session-06","defect_class":"dead_quest","manual_active_minutes":"f:5.771158529166667","manual_correct":false,"manual_scored_minutes":"f:8","manual_session_id":"qa-retest-04-session-05","pair_id":"qa-retest-04-pair-03","pair_sha256":"0e65b3c83af9fa87c443736ccfbc80bd3a482e4b0e0e7b0849a9bf49f5f21329","saved_fraction":"f:0.6064978154520833","saved_minutes":"f:4.851982523616666"},{"assisted_active_minutes":"f:7.7831182388833335","assisted_correct":false,"assisted_scored_minutes":"f:8","assisted_session_id":"qa-retest-04-session-07","defect_class":"unreachable_target","manual_active_minutes":"f:1.3342903104166666","manual_correct":false,"manual_scored_minutes":"f:8","manual_session_id":"qa-retest-04-session-08","pair_id":"qa-retest-04-pair-04","pair_sha256":"11f5ce5a140fae4e14b32c29ea74587c88f744c3dad2742e2fe29e15160962cb","saved_fraction":"f:0","saved_minutes":"f:0"}],"planned_pairs":4,"protocol_failure_pairs":0,"saved_fraction_ci_high":"f:0.6296596829864582","saved_fraction_ci_low":"f:0.1516244538630208","saved_minutes_ci_high":"f:5.037277463891666","saved_minutes_ci_low":"f:1.2129956309041665","time_scoring":"incorrect_uses_active_cap"},"sessions":[{"active_ns":442237987500,"arm":"manual","capped_active_ns":442237987500,"case_id":"endless-sky.cyclic-dependency.development","elapsed_ns":442237987500,"events":[{"kind":"start","monotonic_ns":143605929325916},{"kind":"finish","monotonic_ns":144048167313416}],"evidence_sha256":"5b0f403e31a74c7e149276114748c0ab53f1b2a8444f6632780ba26792d2c746","failure_reasons":[],"final_patch_path":"qa-patches/qa-retest-04-session-01.patch","final_patch_sha256":"e3b0c44298fc1c149afbf4c8996fb92427ae41e4649b934ca495991b7852b855","order":1,"pair_id":"qa-retest-04-pair-01","participant_attested_no_contamination":true,"participant_id":"participant-04","protocol_sha256":"40afa46f4be87f2573148ce3ff12254e3761e51cf8f849fbeb59c2e585ff6cee","protocol_valid":true,"schema_version":"qa-session@1","session_id":"qa-retest-04-session-01","timed_out":false,"verdict":{"correct":false,"failure_reason":"predicate status is violation; target finding remains","native_exit_code":0,"new_deterministic_findings":[],"predicate_status":"violation","reader_round_trip":true,"schema_version":"qa-correctness-verdict@1","submitted_tree_sha256":"5faf5026e226411f4dd3b6e4bcd109d9b57f942cc678aba9cb71e7d5ecd6791a","target_entities_preserved":true,"target_finding_clear":false,"verdict_sha256":"581c7d51ec65dc294fcbd67d20495c5330a2a2eb326daeb71da1d0cc12979c9a"}},{"active_ns":266649397791,"arm":"assisted","capped_active_ns":266649397791,"case_id":"endless-sky.cyclic-dependency.verification","elapsed_ns":266649397791,"events":[{"kind":"start","monotonic_ns":144066386083750},{"kind":"finish","monotonic_ns":144333035481541}],"evidence_sha256":"b128574b7b4636318df698a36636a3cb461c704f4dfad7b6410693759a68c302","failure_reasons":[],"final_patch_path":"qa-patches/qa-retest-04-session-02.patch","final_patch_sha256":"16600ce3b65c415479bd629a6952e73e810c6dc5c8f3b65ad9370d1967f73211","order":2,"pair_id":"qa-retest-04-pair-01","participant_attested_no_contamination":true,"participant_id":"participant-04","protocol_sha256":"40afa46f4be87f2573148ce3ff12254e3761e51cf8f849fbeb59c2e585ff6cee","protocol_valid":true,"schema_version":"qa-session@1","session_id":"qa-retest-04-session-02","timed_out":false,"verdict":{"correct":true,"native_exit_code":0,"new_deterministic_findings":[],"predicate_status":"clear","reader_round_trip":true,"schema_version":"qa-correctness-verdict@1","submitted_tree_sha256":"985156b81f63a146e1db536bb8b8dd8f2d4396095ad7ebb94f08855f4df66acd","target_entities_preserved":true,"target_finding_clear":true,"verdict_sha256":"b715caea786b00a3936cc30d8b0990cb58718e9d0e3f40920aac8875dcc441eb"}},{"active_ns":166645655750,"arm":"assisted","capped_active_ns":166645655750,"case_id":"endless-sky.dangling-reference.development","elapsed_ns":166645655750,"events":[{"kind":"start","monotonic_ns":144646213221833},{"kind":"finish","monotonic_ns":144812858877583}],"evidence_sha256":"7e6cdbf9b0ddb72b050cf7d2c48daf77cb2d5979e6a5412bf4c3e1ad9155ce19","failure_reasons":[],"final_patch_path":"qa-patches/qa-retest-04-session-03.patch","final_patch_sha256":"be23a736f4ef567c834c0f312e4fb5085d81a33a547c9ed7004e1941ad4cb310","order":3,"pair_id":"qa-retest-04-pair-02","participant_attested_no_contamination":true,"participant_id":"participant-04","protocol_sha256":"40afa46f4be87f2573148ce3ff12254e3761e51cf8f849fbeb59c2e585ff6cee","protocol_valid":true,"schema_version":"qa-session@1","session_id":"qa-retest-04-session-03","timed_out":false,"verdict":{"correct":true,"native_exit_code":0,"new_deterministic_findings":[],"predicate_status":"clear","reader_round_trip":true,"schema_version":"qa-correctness-verdict@1","submitted_tree_sha256":"6a7d97625da196932fa28bfcb96639714dc14225b7aff60087afcfeb6abad56c","target_entities_preserved":true,"target_finding_clear":true,"verdict_sha256":"6e8f1ecdc15bb5834aad6b03ad6f3937510bcfe5eba35c99f7e6bc656b5ddd1a"}},{"active_ns":326442060292,"arm":"manual","capped_active_ns":326442060292,"case_id":"endless-sky.dangling-reference.verification","elapsed_ns":326442060292,"events":[{"kind":"start","monotonic_ns":144817249094958},{"kind":"finish","monotonic_ns":145143691155250}],"evidence_sha256":"46be23a95fa871aa9bcc815bcbce9ec2b633609e73363ce19a16e30d6fecfef5","failure_reasons":[],"final_patch_path":"qa-patches/qa-retest-04-session-04.patch","final_patch_sha256":"e3b0c44298fc1c149afbf4c8996fb92427ae41e4649b934ca495991b7852b855","order":4,"pair_id":"qa-retest-04-pair-02","participant_attested_no_contamination":true,"participant_id":"participant-04","protocol_sha256":"40afa46f4be87f2573148ce3ff12254e3761e51cf8f849fbeb59c2e585ff6cee","protocol_valid":true,"schema_version":"qa-session@1","session_id":"qa-retest-04-session-04","timed_out":false,"verdict":{"correct":false,"failure_reason":"predicate status is violation; target finding remains","native_exit_code":0,"new_deterministic_findings":[],"predicate_status":"violation","reader_round_trip":true,"schema_version":"qa-correctness-verdict@1","submitted_tree_sha256":"9fca714e8912c588481298fa3a2f475a7b9553f983ae99eef4c74a97fab26308","target_entities_preserved":true,"target_finding_clear":false,"verdict_sha256":"97a9e0c7cf1b9f2ff57627277eb84cb662e25d2884cd7a0963f29ea521aa35c6"}},{"active_ns":346269511750,"arm":"manual","capped_active_ns":346269511750,"case_id":"endless-sky.dead-quest.verification","elapsed_ns":346269511750,"events":[{"kind":"start","monotonic_ns":145151628243708},{"kind":"finish","monotonic_ns":145497897755458}],"evidence_sha256":"6ceae517a85299d62689d656ee04d5652b8cef8b86cb2b69b7ca509a22a6fe98","failure_reasons":[],"final_patch_path":"qa-patches/qa-retest-04-session-05.patch","final_patch_sha256":"e3b0c44298fc1c149afbf4c8996fb92427ae41e4649b934ca495991b7852b855","order":5,"pair_id":"qa-retest-04-pair-03","participant_attested_no_contamination":true,"participant_id":"participant-04","protocol_sha256":"40afa46f4be87f2573148ce3ff12254e3761e51cf8f849fbeb59c2e585ff6cee","protocol_valid":true,"schema_version":"qa-session@1","session_id":"qa-retest-04-session-05","timed_out":false,"verdict":{"correct":false,"failure_reason":"predicate status is violation; target finding remains","native_exit_code":0,"new_deterministic_findings":[],"predicate_status":"violation","reader_round_trip":true,"schema_version":"qa-correctness-verdict@1","submitted_tree_sha256":"787e1c6c25fbc9d711c8ca628dcf1b9d0dfd362718685172929e0d4140589e03","target_entities_preserved":true,"target_finding_clear":false,"verdict_sha256":"65aa1d8e020a7b2edf0a12f386bfe836a830ff5444d17b99ae78a9792d32a7a0"}},{"active_ns":188881048583,"arm":"assisted","capped_active_ns":188881048583,"case_id":"endless-sky.dead-quest.development","elapsed_ns":188881048583,"events":[{"kind":"start","monotonic_ns":145507737413458},{"kind":"finish","monotonic_ns":145696618462041}],"evidence_sha256":"14ff6f1cc4662d708d1eab22a3a429707f19c89682a50f429db0c7ab694cf299","failure_reasons":[],"final_patch_path":"qa-patches/qa-retest-04-session-06.patch","final_patch_sha256":"5c83824c1fbbd8e9f1c6242e988c26ff894174aac45ed8c42f52798d441efcdf","order":6,"pair_id":"qa-retest-04-pair-03","participant_attested_no_contamination":true,"participant_id":"participant-04","protocol_sha256":"40afa46f4be87f2573148ce3ff12254e3761e51cf8f849fbeb59c2e585ff6cee","protocol_valid":true,"schema_version":"qa-session@1","session_id":"qa-retest-04-session-06","timed_out":false,"verdict":{"correct":true,"native_exit_code":0,"new_deterministic_findings":[],"predicate_status":"clear","reader_round_trip":true,"schema_version":"qa-correctness-verdict@1","submitted_tree_sha256":"e231a68993811c7d0d117d895fc164731ee41f19cdafe2cbb6afcd6a08f8cc8f","target_entities_preserved":true,"target_finding_clear":true,"verdict_sha256":"a1a06c73ac3c7ad6a25536bce26e7ea34b00718dace7f2a450ce3eeae3d5b234"}},{"active_ns":466987094333,"arm":"assisted","capped_active_ns":466987094333,"case_id":"endless-sky.unreachable-target.verification","elapsed_ns":466987094333,"events":[{"kind":"start","monotonic_ns":145706930505375},{"kind":"finish","monotonic_ns":146173917599708}],"evidence_sha256":"4629f9824a7aa2842f7389b93c09963acbb33706ccb34a653d9178aabe265dd4","failure_reasons":[],"final_patch_path":"qa-patches/qa-retest-04-session-07.patch","final_patch_sha256":"434fc898f4fbd0f14082a8dc5f31f25c2f6442b35cc7bd69652c18c91917043c","order":7,"pair_id":"qa-retest-04-pair-04","participant_attested_no_contamination":true,"participant_id":"participant-04","protocol_sha256":"40afa46f4be87f2573148ce3ff12254e3761e51cf8f849fbeb59c2e585ff6cee","protocol_valid":true,"schema_version":"qa-session@1","session_id":"qa-retest-04-session-07","timed_out":false,"verdict":{"correct":false,"failure_reason":"predicate status is violation; target finding remains","native_exit_code":0,"new_deterministic_findings":[],"predicate_status":"violation","reader_round_trip":true,"schema_version":"qa-correctness-verdict@1","submitted_tree_sha256":"32b15b3518a4877989abd991d796e865f6de2d437d6f0bba5a58c2878a3ff88a","target_entities_preserved":true,"target_finding_clear":false,"verdict_sha256":"ed2d75c425d6bfbb8c22c92b007688ea73ef7028c65b46d541f8d73b767ace98"}},{"active_ns":80057418625,"arm":"manual","capped_active_ns":80057418625,"case_id":"endless-sky.unreachable-target.development","elapsed_ns":80057418625,"events":[{"kind":"start","monotonic_ns":146184196678583},{"kind":"finish","monotonic_ns":146264254097208}],"evidence_sha256":"18e584c5d1826f9a47f5510f098f178eef44bbd6ef2a47932c06eb8c22db3272","failure_reasons":[],"final_patch_path":"qa-patches/qa-retest-04-session-08.patch","final_patch_sha256":"e3b0c44298fc1c149afbf4c8996fb92427ae41e4649b934ca495991b7852b855","order":8,"pair_id":"qa-retest-04-pair-04","participant_attested_no_contamination":true,"participant_id":"participant-04","protocol_sha256":"40afa46f4be87f2573148ce3ff12254e3761e51cf8f849fbeb59c2e585ff6cee","protocol_valid":true,"schema_version":"qa-session@1","session_id":"qa-retest-04-session-08","timed_out":false,"verdict":{"correct":false,"failure_reason":"predicate status is violation; target finding remains","native_exit_code":0,"new_deterministic_findings":[],"predicate_status":"violation","reader_round_trip":true,"schema_version":"qa-correctness-verdict@1","submitted_tree_sha256":"39a61b7e4020451bdbe76f89f3cf6cecfd9e9ba343fbd6ab6fead6639d952893","target_entities_preserved":true,"target_finding_clear":false,"verdict_sha256":"34b45596b98a709c1cca5d252dd8d313598745ac4930d426e346b07cab23898e"}}]}
